gpi_pack/TNutil.py
gpi_pack/TarNet.py
gpi_pack/__init__.py
gpi_pack/llm.py
gpi_pack-0.1.0.dist-info/LICENSE
gpi_pack-0.1.0.dist-info/METADATA
gpi_pack-0.1.0.dist-info/WHEEL
gpi_pack-0.1.0.dist-info/top_level.txt
gpi_pack-0.1.0.dist-info/RECORD
