Metadata-Version: 2.2
Name: gpi_pack
Version: 0.1.0
Summary: A brief description of your package
Author-email: Kentaro Nakamura <knakamura@g.harvard.edu>
License: MIT
Project-URL: Homepage, https://gpi-pack.github.io/
Project-URL: Bug Tracker, https://github.com/gpi-pack/gpi_pack/issues
Classifier: Development Status :: 3 - Alpha
Classifier: Intended Audience :: Developers
Classifier: License :: OSI Approved :: MIT License
Classifier: Programming Language :: Python :: 3
Classifier: Programming Language :: Python :: 3.8
Classifier: Programming Language :: Python :: 3.9
Classifier: Programming Language :: Python :: 3.10
Classifier: Programming Language :: Python :: 3.11
Requires-Python: >=3.8
License-File: LICENSE
Requires-Dist: numpy>=1.22.0
Requires-Dist: scipy>=1.8.0
Requires-Dist: matplotlib>=3.5.0
Requires-Dist: torch>=2.0.0
Requires-Dist: scikit-learn>=1.0.0
Requires-Dist: pandas>=1.4.0
Requires-Dist: transformers>=4.20.0
Requires-Dist: tqdm>=4.60.0
Requires-Dist: accelerate>=0.15.0
Requires-Dist: patsy>=0.5.2
Provides-Extra: dev
Requires-Dist: pytest>=7.0.0; extra == "dev"
Requires-Dist: pytest-cov>=4.0.0; extra == "dev"
Requires-Dist: black>=23.0.0; extra == "dev"
Requires-Dist: mypy>=1.0.0; extra == "dev"
Requires-Dist: isort>=5.0.0; extra == "dev"
